{
  "__weakref__": null,
  "agreement": [
    "417_582"
  ],
  "annotation": {
    "n_repetitions": 1,
    "rep": 0
  },
  "broken": false,
  "current_offer": [
    "417_582"
  ],
  "current_proposer": "nRXUKjUnU",
  "current_proposer_agent": null,
  "effective_scenario_name": "156765854084395445",
  "error_details": "",
  "execution_time": 3.2592676999993273,
  "has_error": false,
  "kalai_optimality": 0.9269157307883567,
  "last_negotiator": "RVFitter@0",
  "last_thread": "",
  "max_utils": [
    1.0,
    1.0
  ],
  "max_welfare_optimality": 0.9928592682275805,
  "mechanism_name": "156765854084395445",
  "mechanism_type": "negmas.sao.mechanism.SAOMechanism",
  "modified_kalai_optimality": 0.7314621683893315,
  "n_acceptances": 2,
  "n_negotiators": 2,
  "n_repetitions": 1,
  "n_steps": 393,
  "nash_optimality": 0.9898306769815991,
  "negotiator_ids": [
    "nRXUKjUnU",
    "nOz0xS4ke"
  ],
  "negotiator_names": [
    "RVFitter@0",
    "Boulware@1"
  ],
  "negotiator_time_limit": Infinity,
  "negotiator_times": [
    2.8797167999837257,
    0.207524099987495
  ],
  "negotiator_types": [
    "anl.anl2024.negotiators.builtins.rv_fitter.RVFitter",
    "anl.anl2024.negotiators.builtins.wrappers.Boulware"
  ],
  "new_offerer_agents": [
    null
  ],
  "new_offers": [
    [
      "nRXUKjUnU",
      [
        "417_582"
      ]
    ]
  ],
  "params": null,
  "pareto_optimality": 1.0,
  "partners": [
    "RVFitter",
    "Boulware"
  ],
  "pend": 0,
  "pend_per_second": 0,
  "relative_time": 0.8147208121827412,
  "rep": 0,
  "reserved_values": [
    0.06601418250027982,
    0.43240100763022393
  ],
  "results": null,
  "run_id": "156765854084395445",
  "running": false,
  "scenario": "S5",
  "started": true,
  "step": 320,
  "step_time_limit": Infinity,
  "threads": {},
  "time": 3.259029799999553,
  "time_limit": 60,
  "timedout": false,
  "utilities": [
    0.2669611504377538,
    0.7948713508422066
  ],
  "waiting": false
}